README.md
__init__.py
manage.py
finetune_worker/__init__.py
finetune_worker/celery/__init__.py
finetune_worker/celery/app.py
finetune_worker/celery/config.py
finetune_worker/celery/tasks.py
finetune_worker/stream/sse.py
finetune_worker/stream/tasks.py
finetune_worker/stream/utils.py
finetune_worker/stream/ws.py
finetune_worker-0.0.2.dist-info/METADATA
finetune_worker-0.0.2.dist-info/WHEEL
finetune_worker-0.0.2.dist-info/entry_points.txt
finetune_worker-0.0.2.dist-info/licenses/LICENSE
finetune_worker-0.0.2.dist-info/RECORD
