Metadata-Version: 2.4
Name: finetune-worker
Version: 0.0.2
Summary: Python worker client for communicating with finetune.build's API
Project-URL: Homepage, https://github.com/finetune-build/Worker
Project-URL: Issues, https://github.com/finetune-build/Worker/issues
Author-email: Peter Pak <ppak10@gmail.com>
License-File: LICENSE
Classifier: Operating System :: OS Independent
Classifier: Programming Language :: Python :: 3
Requires-Python: >=3.9
Requires-Dist: aiohttp
Requires-Dist: celery
Requires-Dist: python-dotenv
Requires-Dist: sqlalchemy
Requires-Dist: watchdog
Requires-Dist: websockets
